brunodb/__init__.py
brunodb/bulk_load_postgres.py
brunodb/cars_example.py
brunodb/database.py
brunodb/database_generic.py
brunodb/database_postgres.py
brunodb/database_sqlite.py
brunodb/format_query.py
brunodb/graceful_stop.py
brunodb/perf_test.py
brunodb/postgres_utils.py
brunodb/query.py
brunodb/run_cars_example.py
brunodb/sqlite_utils.py
brunodb/table.py
brunodb-0.3.2.dist-info/LICENSE.txt
brunodb-0.3.2.dist-info/METADATA
brunodb-0.3.2.dist-info/WHEEL
brunodb-0.3.2.dist-info/top_level.txt
brunodb-0.3.2.dist-info/RECORD
