Metadata-Version: 2.1
Name: brunodb
Version: 0.3.2
Summary: Useful wrapper for SQLite
Home-page: https://github.com/dave31415/brunodb
Author: David Johnston
Author-email: dave31415@gmail.com
License: MIT
Download-URL: https://pypi.org/project/brunodb/
Keywords: SQLite
Platform: UNKNOWN
License-File: LICENSE.txt
Requires-Dist: pytest
Requires-Dist: psycopg2-binary
